<annotation>
	<folder>4.14</folder>
	<filename>F000620-134810193.jpg</filename>
	<path>C:\Users\Administrator\Desktop\4.14\F000620-134810193.jpg</path>
	<source>
		<database>Unknown</database>
	</source>
	<size>
		<width>640</width>
		<height>512</height>
		<depth>1</depth>
	</size>
	<segmented>0</segmented>
	<object>
		<name>target</name>
		<pose>Unspecified</pose>
		<truncated>0</truncated>
		<difficult>0</difficult>
		<bndbox>
			<xmin>351</xmin>
			<ymin>231</ymin>
			<xmax>388</xmax>
			<ymax>239</ymax>
		</bndbox>
	</object>
	<object>
		<name>point</name>
		<pose>Unspecified</pose>
		<truncated>0</truncated>
		<difficult>0</difficult>
		<bndbox>
			<xmin>244</xmin>
			<ymin>236</ymin>
			<xmax>255</xmax>
			<ymax>241</ymax>
		</bndbox>
	</object>
</annotation>