<annotation>
	<folder>dataselect</folder>
	<filename>014845-090544109.jpg</filename>
	<path>E:\data\dataselect\014845-090544109.jpg</path>
	<source>
		<database>Unknown</database>
	</source>
	<size>
		<width>640</width>
		<height>512</height>
		<depth>1</depth>
	</size>
	<segmented>0</segmented>
	<object>
		<name>target</name>
		<pose>Unspecified</pose>
		<truncated>0</truncated>
		<difficult>0</difficult>
		<bndbox>
			<xmin>114</xmin>
			<ymin>294</ymin>
			<xmax>142</xmax>
			<ymax>309</ymax>
		</bndbox>
	</object>
	<object>
		<name>target</name>
		<pose>Unspecified</pose>
		<truncated>0</truncated>
		<difficult>0</difficult>
		<bndbox>
			<xmin>153</xmin>
			<ymin>301</ymin>
			<xmax>176</xmax>
			<ymax>311</ymax>
		</bndbox>
	</object>
	<object>
		<name>target</name>
		<pose>Unspecified</pose>
		<truncated>0</truncated>
		<difficult>0</difficult>
		<bndbox>
			<xmin>540</xmin>
			<ymin>336</ymin>
			<xmax>578</xmax>
			<ymax>354</ymax>
		</bndbox>
	</object>
</annotation>