<annotation>
	<folder>imgsum</folder>
	<filename>F001835-094829233.jpg</filename>
	<path>H:\imgsum\F001835-094829233.jpg</path>
	<source>
		<database>Unknown</database>
	</source>
	<size>
		<width>640</width>
		<height>512</height>
		<depth>1</depth>
	</size>
	<segmented>0</segmented>
	<object>
		<name>target</name>
		<pose>Unspecified</pose>
		<truncated>0</truncated>
		<difficult>0</difficult>
		<bndbox>
			<xmin>158</xmin>
			<ymin>276</ymin>
			<xmax>169</xmax>
			<ymax>282</ymax>
		</bndbox>
	</object>
	<object>
		<name>target</name>
		<pose>Unspecified</pose>
		<truncated>0</truncated>
		<difficult>0</difficult>
		<bndbox>
			<xmin>604</xmin>
			<ymin>210</ymin>
			<xmax>610</xmax>
			<ymax>216</ymax>
		</bndbox>
	</object>
	<object>
		<name>point</name>
		<pose>Unspecified</pose>
		<truncated>0</truncated>
		<difficult>0</difficult>
		<bndbox>
			<xmin>572</xmin>
			<ymin>273</ymin>
			<xmax>582</xmax>
			<ymax>278</ymax>
		</bndbox>
	</object>
	<object>
		<name>island</name>
		<pose>Unspecified</pose>
		<truncated>0</truncated>
		<difficult>0</difficult>
		<bndbox>
			<xmin>398</xmin>
			<ymin>94</ymin>
			<xmax>433</xmax>
			<ymax>125</ymax>
		</bndbox>
	</object>
	<object>
		<name>target</name>
		<pose>Unspecified</pose>
		<truncated>0</truncated>
		<difficult>0</difficult>
		<bndbox>
			<xmin>312</xmin>
			<ymin>242</ymin>
			<xmax>319</xmax>
			<ymax>249</ymax>
		</bndbox>
	</object>
	<object>
		<name>island</name>
		<pose>Unspecified</pose>
		<truncated>0</truncated>
		<difficult>0</difficult>
		<bndbox>
			<xmin>503</xmin>
			<ymin>59</ymin>
			<xmax>568</xmax>
			<ymax>84</ymax>
		</bndbox>
	</object>
</annotation>